orange3_nlp_jezyk_polski-0.0.1.dist-info/licenses/LICENSE
orangecontrib/__init__.py
orangecontrib/nlp/__init__.py
orangecontrib/nlp/widgets/__init__.py
orangecontrib/nlp/widgets/owanaliza_sentymentu.py
orangecontrib/nlp/widgets/icons/nlp-analiza-sentymentu.svg
orangecontrib/nlp/widgets/icons/nlp-orange.svg
tests/test_widgets.py
orange3_nlp_jezyk_polski-0.0.1.dist-info/METADATA
orange3_nlp_jezyk_polski-0.0.1.dist-info/WHEEL
orange3_nlp_jezyk_polski-0.0.1.dist-info/entry_points.txt
orange3_nlp_jezyk_polski-0.0.1.dist-info/top_level.txt
orange3_nlp_jezyk_polski-0.0.1.dist-info/RECORD
